xgbexcel/__init__.py
xgbexcel/convert.py
xgbexcel-0.1.0.dist-info/licenses/LICENSE
xgbexcel-0.1.0.dist-info/METADATA
xgbexcel-0.1.0.dist-info/WHEEL
xgbexcel-0.1.0.dist-info/top_level.txt
xgbexcel-0.1.0.dist-info/RECORD
