Metadata-Version: 2.4
Name: xgbexcel
Version: 0.1.0
Summary: Convert XGBRegressor or XGBClassifier models to an Excel formula expression.
Home-page: https://github.com/KalinNonchev/xgbexcel
Author: KalinNonchev
Author-email: boo@foo.com
License: MIT License
Requires-Python: >=3.8
License-File: LICENSE
Requires-Dist: xgboost
Dynamic: author
Dynamic: author-email
Dynamic: description
Dynamic: description-content-type
Dynamic: home-page
Dynamic: license
Dynamic: license-file
Dynamic: requires-dist
Dynamic: requires-python
Dynamic: summary
